RRPad/ReplicationReflectionPad1d.py
RRPad/ReplicationReflectionPad2d.py
RRPad/__init__.py
rrpad-0.0.2.dist-info/licenses/LICENSE
rrpad-0.0.2.dist-info/METADATA
rrpad-0.0.2.dist-info/WHEEL
rrpad-0.0.2.dist-info/top_level.txt
rrpad-0.0.2.dist-info/RECORD
